README.txt
setup.cfg
setup.py
simplegeo/__init__.py
simplegeo/_version.py
simplegeo/json.py
simplegeo/models.py
simplegeo/util.py
simplegeo.egg-info/PKG-INFO
simplegeo.egg-info/SOURCES.txt
simplegeo.egg-info/dependency_links.txt
simplegeo.egg-info/not-zip-safe
simplegeo.egg-info/requires.txt
simplegeo.egg-info/top_level.txt
simplegeo/context/__init__.py
simplegeo/contrib/__init__.py
simplegeo/contrib/google.py
simplegeo/places/__init__.py
simplegeo/places/places_10.py
simplegeo/places/places_12.py
simplegeo/shared/__init__.py
simplegeo/storage/__init__.py
simplegeo/test/__init__.py
simplegeo/test/client/__init__.py
simplegeo/test/client/test_client.py
simplegeo/test/client/test_context.py
simplegeo/test/client/test_places.py
simplegeo/test/models/__init__.py
simplegeo/test/models/test_feature.py
simplegeo/test/models/test_record.py