Metadata-Version: 1.0
Name: simplegeo
Version: 3.0.126
Summary: Library for interfacing with SimpleGeo's API
Home-page: http://github.com/simplegeo/python-simplegeo
Author: Zooko Wilcox-O'Hearn and Ben Standefer
Author-email: ben@simplegeo.com
License: MIT License
Keywords: simplegeo
Platform: UNKNOWN
